skit_matploty/__init__.py
skit_matploty/snippets.py
skit_matploty-0.1.0.dist-info/licenses/LICENSE
skit_matploty-0.1.0.dist-info/METADATA
skit_matploty-0.1.0.dist-info/WHEEL
skit_matploty-0.1.0.dist-info/top_level.txt
skit_matploty-0.1.0.dist-info/RECORD
