Metadata-Version: 2.4
Name: skit-matploty
Version: 0.1.0
Summary: A package to print ML/Matplotlib code snippets for copy-pasting.
Author-email: Your Name <you@example.com>
Classifier: Programming Language :: Python :: 3
Classifier: License :: OSI Approved :: MIT License
Classifier: Operating System :: OS Independent
Requires-Python: >=3.8
License-File: LICENSE
Dynamic: license-file
